{
    "name":"base16-Cupcake",
    "version":"1.0",
    "description":"base16-Cupcake",
    "originator":"Chris Kempson (http://chriskempson.com) - cupcake",
    "colors":[
        {"name": "Background(Read Only)", "color":"#252620" },
        {"name": "Search result background", "color":"#DCB16C" },
        {"name": "Search result background (highlighted)", "color":"#d8d5dd" },
        {"name": "Fold Square", "color":"#bfb9c6", "secondcolor":"#fbf1f2" },
        {"name": "Fold Cross", "color":"#FFFFFF", "secondcolor":"#fbf1f2" },
        {"name": "Indentation Guide", "color":"#bfb9c6" },
        {"name": "Indicator Margin", "color":"#3B3A32" },
        {"name": "Indicator Margin(Separator)", "color":"#3B3A32" },
        {"name": "Tooltip Border", "color":"#979792" },
        {"name": "Tooltip Pager Top", "color":"#292A25" },
        {"name": "Tooltip Pager Bottom", "color":"#292A25" },
        {"name": "Tooltip Pager Triangle", "color":"#C7C7C2" },
        {"name": "Tooltip Pager Text", "color":"#C7C7C2" },
        {"name": "Notification Border", "color":"#979792" },
        {"name": "Bookmarks", "color":"#FDD99B", "secondcolor":"#000000" },
        {"name": "Underline(Error)", "color":"#FF0000" },
        {"name": "Underline(Warning)", "color":"#719ECF" },
        {"name": "Underline(Suggestion)", "color":"#4D9A06" },
        {"name": "Underline(Hint)", "color":"#8AE233" },
        {"name": "Quick Diff(Dirty)", "color":"#A3B367" },
        {"name": "Quick Diff(Changed)", "color":"#A4E22E" },
        {"name": "Brace Matching(Rectangle)", "color":"#6698CC", "secondcolor":"#AACBEE" },
        {"name": "Usages(Rectangle)", "color":"#527F99", "secondcolor":"#527F99", "bordercolor":"#527F99" },
        {"name": "Changing usages(Rectangle)", "color":"#996D74", "secondcolor":"#996D74", "bordercolor":"#996D74" },
        {"name": "Breakpoint Marker", "color":"#6F3535", "bordercolor":"#7A3939" },
        {"name": "Breakpoint Marker(Invalid)", "color":"#604242", "bordercolor":"#6A4A4A" },
        {"name": "Breakpoint Marker(Disabled)", "color":"#707070", "bordercolor":"#7B7B7B" },
        {"name": "Debugger Current Line Marker", "color":"#68674C", "bordercolor":"#737254" },
        {"name": "Debugger Stack Line Marker", "color":"#5C6B4D", "bordercolor":"#657655" },
        {"name": "Primary Link", "color":"#8b8198", "secondcolor":"#7F4981" },
        {"name": "Primary Link(Highlighted)", "color":"#8b8198", "secondcolor":"#B067B3" },
        {"name": "Secondary Link", "color":"#8b8198", "secondcolor":"#262128" },
        {"name": "Secondary Link(Highlighted)", "color":"#8b8198", "secondcolor":"#4E4552" },
        {"name": "Current Line Marker", "color":"#313129" },
        {"name": "Current Line Marker(Inactive)", "color":"#2F2F28" },
        {"name": "Column Ruler", "color":"#575852" },
        {"name": "Completion Matching Substring", "color":"#BA3372" },
        {"name": "Completion Border", "color":"#C9C9C9" },
        {"name": "Completion Border(Inactive)", "color":"#BEBEBE" },
        {"name": "Message Bubble Error Marker", "color":"#B28D37" },
        {"name": "Message Bubble Error Tag", "color":"#E3A5A0", "secondcolor":"#000000" },
        {"name": "Message Bubble Error Tooltip", "color":"#E3A5A0" },
        {"name": "Message Bubble Error Line", "color":"#7A645C" },
        {"name": "Message Bubble Error Counter", "color":"#000000", "secondcolor":"#E3A5A0" },
        {"name": "Message Bubble Error IconMargin", "color":"#725C54", "bordercolor":"#805B4D" },
        {"name": "Message Bubble Warning Marker", "color":"#B28D37" },
        {"name": "Message Bubble Warning Tag", "color":"#EEE79D", "secondcolor":"#000000" },
        {"name": "Message Bubble Warning Tooltip", "color":"#EEE79D" },
        {"name": "Message Bubble Warning Line", "color":"#807E5C" },
        {"name": "Message Bubble Warning Counter", "color":"#000000", "secondcolor":"#EEE79D" },
        {"name": "Message Bubble Warning IconMargin", "color":"#777553", "bordercolor":"#948E51" }    ],
    "text":[
        {"name": "Plain Text", "fore":"#8b8198", "back":"#fbf1f2" },
        {"name": "Selected Text", "back":"#49483E" },
        {"name": "Selected Text(Inactive)", "back":"#383830" },
        {"name": "Collapsed Text", "fore":"#bfb9c6", "back":"#fbf1f2" },
        {"name": "Line Numbers", "fore":"#BCBCBC", "back":"#fbf1f2" },
        {"name": "Punctuation", "fore":"#8b8198" },
        {"name": "Punctuation(Brackets)", "fore":"#8b8198" },
        {"name": "Comment(Line)", "fore":"#bfb9c6" },
        {"name": "Comment(Block)", "fore":"#bfb9c6" },
        {"name": "Comment(Doc)", "fore":"#A3B367" },
        {"name": "Comment(DocTag)", "fore":"#A3B367" },
        {"name": "Comment Tag", "fore":"#bfb9c6", "weight":"Bold" },
        {"name": "Excluded Code", "fore":"#bfb9c6" },
        {"name": "String", "fore":"#A3B367" },
        {"name": "String(Escape)", "fore":"#A5AB34" },
        {"name": "String(C# @ Verbatim)", "fore":"#A3B367" },
        {"name": "Number", "fore":"#A3B367" },
        {"name": "Preprocessor", "fore":"#D57E85" },
        {"name": "Preprocessor(Region Name)", "fore":"#D57E85" },
        {"name": "Xml Text", "fore":"#8b8198" },
        {"name": "Xml Delimiter", "fore":"#8b8198" },
        {"name": "Xml Name", "fore":"#EBB790" },
        {"name": "Xml Attribute", "fore":"#8b8198" },
        {"name": "Xml Attribute Quotes", "fore":"#A3B367" },
        {"name": "Xml Attribute Value", "fore":"#A3B367" },
        {"name": "Xml Comment", "fore":"#bfb9c6" },
        {"name": "Xml CData Section", "fore":"#8b8198" },
        {"name": "Tooltip Text", "fore":"#8b8198", "back":"#272725" },
        {"name": "Notification Text", "fore":"#8b8198", "back":"#272725" },
        {"name": "Completion Selected Text(Inactive)", "fore":"#FFFFFF", "back":"#FFFFFF" },
        {"name": "Keyword(Access)", "fore":"#A3B367" },
        {"name": "Keyword(Type)", "fore":"#DCB16C" },
        {"name": "Keyword(Operator)", "fore":"#D57E85" },
        {"name": "Keyword(Selection)", "fore":"#BB99B4" },
        {"name": "Keyword(Iteration)", "fore":"#BB99B4" },
        {"name": "Keyword(Jump)", "fore":"#BB99B4" },
        {"name": "Keyword(Context)", "fore":"#BB99B4" },
        {"name": "Keyword(Exception)", "fore":"#69A9A7" },
        {"name": "Keyword(Modifiers)", "fore":"#BB99B4" },
        {"name": "Keyword(Constants)", "fore":"#EBB790" },
        {"name": "Keyword(Void)", "fore":"#DCB16C" },
        {"name": "Keyword(Namespace)", "fore":"#BB99B4" },
        {"name": "Keyword(Property)", "fore":"#A3B367" },
        {"name": "Keyword(Declaration)", "fore":"#A3B367" },
        {"name": "Keyword(Parameter)", "fore":"#BB99B4" },
        {"name": "Keyword(Operator Declaration)", "fore":"#D57E85" },
        {"name": "Keyword(Other)", "fore":"#BB99B4" },
        {"name": "User Types", "fore":"#DCB16C" },
        {"name": "User Types(Enums)", "fore":"#DCB16C" },
        {"name": "User Types(Interfaces)", "fore":"#DCB16C" },
        {"name": "User Types(Delegates)", "fore":"#DCB16C" },
        {"name": "User Types(Value types)", "fore":"#DCB16C" },
        {"name": "User Types(Type parameters)", "fore":"#DCB16C" },
        {"name": "User Field Usage", "fore":"#7297B9" },
        {"name": "User Field Declaration", "fore":"#7297B9" },
        {"name": "User Property Usage", "fore":"#7297B9" },
        {"name": "User Property Declaration", "fore":"#7297B9" },
        {"name": "User Event Usage", "fore":"#D57E85" },
        {"name": "User Event Declaration", "fore":"#D57E85" },
        {"name": "User Method Usage", "fore":"#8b8198" },
        {"name": "User Method Declaration", "fore":"#8b8198" },
        {"name": "User Parameter Usage", "fore":"#8b8198" },
        {"name": "User Parameter Declaration", "fore":"#8b8198" },
        {"name": "User Variable Usage", "fore":"#8b8198" },
        {"name": "User Variable Declaration", "fore":"#8b8198" },
        {"name": "Syntax Error", "fore":"#F8F8EF", "back":"#DCB16C" },
        {"name": "String Format Items", "fore":"#8b8198" },
        {"name": "Breakpoint Text", "fore":"#FFFFFF", "back":"#6F3535" },
        {"name": "Debugger Current Statement", "fore":"#FFFFFF", "back":"#68674C" },
        {"name": "Debugger Stack Line", "fore":"#FFFFFF", "back":"#5C6B4D" },
        {"name": "Diff Line(Added)", "fore":"#00898B" },
        {"name": "Diff Line(Removed)", "fore":"#000000" },
        {"name": "Diff Line(Changed)", "fore":"#000000" },
        {"name": "Diff Header", "fore":"#008000" },
        {"name": "Diff Header(Separator)", "fore":"#0000FF", "weight":"Bold" },
        {"name": "Diff Header(Old)", "fore":"#008000", "weight":"Bold" },
        {"name": "Diff Header(New)", "fore":"#008000", "weight":"Bold" },
        {"name": "Diff Location", "fore":"#FB8A00", "weight":"Bold" },
        {"name": "Html Attribute Name", "fore":"#8b8198" },
        {"name": "Html Attribute Value", "fore":"#A3B367" },
        {"name": "Html Comment", "fore":"#bfb9c6" },
        {"name": "Html Element Name", "fore":"#DCB16C" },
        {"name": "Html Entity", "fore":"#D57E85" },
        {"name": "Html Operator", "fore":"#DCB16C" },
        {"name": "Html Server-Side Script", "fore":"#8b8198", "back":"#363732" },
        {"name": "Html Tag Delimiter", "fore":"#8b8198" },
        {"name": "Razor Code", "fore":"#8b8198", "back":"#363732" },
        {"name": "Css Comment", "fore":"#bfb9c6", "weight":"Bold" },
        {"name": "Css Property Value", "fore":"#A3B367", "weight":"Bold" },
        {"name": "Css Selector", "fore":"#bfb9c6", "weight":"Bold" },
        {"name": "Css String Value", "fore":"#000000", "weight":"Bold" },
        {"name": "Css Keyword", "fore":"#DCB16C", "weight":"Bold" },
        {"name": "Script Comment", "fore":"#bfb9c6" },
        {"name": "Script Keyword", "fore":"#DCB16C" },
        {"name": "Script Number", "fore":"#A3B367" },
        {"name": "Script String", "fore":"#A3B367" }
    ]
}
